ime_utils/__init__.py
ime_utils/__main__.py
ime_utils/cli.py
ime_utils/converter/__init__.py
ime_utils/core/__init__.py
ime_utils/core/base.py
ime_utils/core/models.py
ime_utils/core/utils.py
ime_utils/parser/__init__.py
ime_utils/parser/baidu.py
ime_utils/parser/huayu.py
ime_utils/parser/qq.py
ime_utils/parser/sogou.py
ime_utils/pinyin/__init__.py
ime_utils/pinyin/baidu.py
ime_utils/pinyin/huayu.py
ime_utils/pinyin/syllable.py
ime_utils-0.2.4.dist-info/WHEEL
ime_utils-0.2.4.dist-info/entry_points.txt
ime_utils-0.2.4.dist-info/METADATA
ime_utils-0.2.4.dist-info/RECORD
