Metadata-Version: 2.4
Name: ime-utils
Version: 0.2.4
Summary: Chinese IME ciku (aka cell wordlist file) parsing tool
License-Expression: MIT
Requires-Python: >=3.10
Project-URL: Changelog, https://github.com/hantang/ime-utils/blob/main/CHANGELOG.md
Project-URL: Documentation, https://github.com/hantang/ime-utils
Project-URL: Homepage, https://github.com/hantang/ime-utils
Project-URL: Issues, https://github.com/hantang/ime-utils/issues
Project-URL: Repository, https://github.com/hantang/ime-utils.git
